invoke_junkpile/__init__.py
invoke_junkpile/__main__.py
invoke_junkpile-1.0.3.dist-info/METADATA
invoke_junkpile-1.0.3.dist-info/WHEEL
invoke_junkpile-1.0.3.dist-info/entry_points.txt
invoke_junkpile-1.0.3.dist-info/top_level.txt
invoke_junkpile-1.0.3.dist-info/RECORD
