Metadata-Version: 2.4
Name: invoke-junkpile
Version: 1.0.3
Summary: PowerShell obfuscation through stacked junk logic, dead code, and variable chaos.
Author-email: Tim Peck <pypi@pf5.co>
License: MIT
Keywords: powershell,obfuscation,redteam,cybersecurity
Classifier: Programming Language :: Python :: 3
Classifier: License :: OSI Approved :: MIT License
Classifier: Topic :: Security
Classifier: Topic :: Utilities
Requires-Python: >=3.8
